setup.py
parinx/__init__.py
parinx/errors.py
parinx/parser.py
parinx/utils.py
parinx.egg-info/PKG-INFO
parinx.egg-info/SOURCES.txt
parinx.egg-info/dependency_links.txt
parinx.egg-info/entry_points.txt
parinx.egg-info/top_level.txt
tests/__init__.py
tests/test_parser.py