Metadata-Version: 1.0
Name: parinx
Version: 0.1.1
Summary: Parinx implements a basic Sphinx docstring parser language                    which providesa interface to extract the relavant parameter.                  You might find it most useful for tasks involving automated                   data extraction from sphinx docs.
Home-page: https://github.com/rahulrrixe/parinx
Author: Rahul Ranjan
Author-email: rahul.rrixe@gmail.com
License: Apache License (2.0)
Keywords: sphinx,docstring,parser
Platform: UNKNOWN
